erica_csv_converter/__init__.py
erica_csv_converter/converter.py
erica_csv_converter-0.1.4.dist-info/entry_points.txt
erica_csv_converter-0.1.4.dist-info/WHEEL
erica_csv_converter-0.1.4.dist-info/METADATA
erica_csv_converter-0.1.4.dist-info/RECORD
