Metadata-Version: 2.1
Name: erica-csv-converter
Version: 0.1.4
Summary: Convert CSV to Json
Author: Erica Brandão
Author-email: erica_martins_brandao@yahoo.com.br
Requires-Python: >=3.10,<4.0
Classifier: Programming Language :: Python :: 3
Classifier: Programming Language :: Python :: 3.10
Requires-Dist: click (>=8.0.3,<9.0.0)
Requires-Dist: pandas (>=1.3.5,<2.0.0)
